dataset_viewer/__init__.py
dataset_viewer/dataset.py
dataset_viewer/viewer.py
dataset_viewer-1.0.0.dist-info/LICENSE
dataset_viewer-1.0.0.dist-info/METADATA
dataset_viewer-1.0.0.dist-info/WHEEL
dataset_viewer-1.0.0.dist-info/top_level.txt
dataset_viewer-1.0.0.dist-info/RECORD
